subprocess_connection.py
subprocess_connection/__init__.py
subprocess_connection/py.typed
subprocess_connection-0.0.6.dist-info/LICENSE
subprocess_connection-0.0.6.dist-info/METADATA
subprocess_connection-0.0.6.dist-info/WHEEL
subprocess_connection-0.0.6.dist-info/top_level.txt
subprocess_connection-0.0.6.dist-info/zip-safe
subprocess_connection-0.0.6.dist-info/RECORD
